stancer/__init__.py
stancer/auth.py
stancer/card.py
stancer/config.py
stancer/customer.py
stancer/device.py
stancer/dispute.py
stancer/payment.py
stancer/refund.py
stancer/sepa.py
stancer/version.py
stancer/core/__init__.py
stancer/core/abstract_amount.py
stancer/core/abstract_country.py
stancer/core/abstract_last4.py
stancer/core/abstract_name.py
stancer/core/abstract_object.py
stancer/core/abstract_search.py
stancer/core/request.py
stancer/core/singleton.py
stancer/core/decorators/__init__.py
stancer/core/decorators/populate_on_call.py
stancer/core/decorators/validate_type.py
stancer/core/helpers/__init__.py
stancer/core/helpers/coerce_status.py
stancer/core/helpers/coerce_uuid.py
stancer/core/payment/__init__.py
stancer/core/payment/auth.py
stancer/core/payment/page.py
stancer/core/payment/refund.py
stancer/exceptions/__init__.py
stancer/exceptions/base.py
stancer/exceptions/http.py
stancer/exceptions/invalid_value.py
stancer/exceptions/type_error.py
stancer/status/__init__.py
stancer/status/auth.py
stancer/status/base.py
stancer/status/payment.py
stancer/status/refund.py
tests/TestHelper.py
tests/__init__.py
tests/test_auth.py
tests/test_auth_status.py
tests/test_card.py
tests/test_config.py
tests/test_customer.py
tests/test_device.py
tests/test_dispute.py
tests/test_exceptions.py
tests/test_issues.py
tests/test_payment.py
tests/test_payment_status.py
tests/test_refund.py
tests/test_refund_status.py
tests/test_sepa.py
tests/test_stub_object.py
tests/test_stub_search.py
tests/test_stub_with_default.py
tests/core/__init__.py
tests/core/test_abstract_amount.py
tests/core/test_abstract_country.py
tests/core/test_abstract_name.py
tests/core/test_abstract_object.py
tests/core/test_abstract_search.py
tests/core/test_request.py
tests/functional/TestHelper.py
tests/functional/__init__.py
tests/functional/test_card.py
tests/functional/test_customer.py
tests/functional/test_dispute.py
tests/functional/test_payment.py
tests/functional/test_refund.py
tests/stub/__init__.py
stancer-1.0.0.dist-info/LICENSE
stancer-1.0.0.dist-info/METADATA
stancer-1.0.0.dist-info/WHEEL
stancer-1.0.0.dist-info/top_level.txt
stancer-1.0.0.dist-info/RECORD
